quack_better.py
mllite/__init__.py
mllite/quack_better.py
mllite-0.1789.dist-info/LICENSE
mllite-0.1789.dist-info/METADATA
mllite-0.1789.dist-info/WHEEL
mllite-0.1789.dist-info/top_level.txt
mllite-0.1789.dist-info/RECORD
