Metadata-Version: 2.1
Name: mllite
Version: 0.1789
Summary: MLLite
Home-page: https://github.com/mllite/
Author: Antoine CARME
Author-email: antoine.carme@outlook.com
Requires-Python: >=3
License-File: LICENSE
